peepomap/__init__.py
peepomap/__main__.py
peepomap/colormaps.py
peepomap/exceptions.py
peepomap/plot.py
peepomap/tools.py
peepomap-0.2.2.dist-info/METADATA
peepomap-0.2.2.dist-info/WHEEL
peepomap-0.2.2.dist-info/licenses/LICENSE
peepomap-0.2.2.dist-info/RECORD
