Metadata-Version: 2.4
Name: peepomap
Version: 0.2.2
Summary: Just some extra Peepo-Powered Matplotlib colormaps and tools.
Project-URL: Homepage, https://github.com/opteric/peepomap
Project-URL: Repository, https://github.com/opteric/peepomap
Project-URL: Issues, https://github.com/opteric/peepomap/issues
Author-email: Eric Miguel <eric.mrib@gmail.com>
License: MIT
License-File: LICENSE
Keywords: cartopy,colormap,matplotlib,scientific computing,visualization
Classifier: Development Status :: 4 - Beta
Classifier: Intended Audience :: Science/Research
Classifier: License :: OSI Approved :: MIT License
Classifier: Programming Language :: Python :: 3
Classifier: Programming Language :: Python :: 3.12
Classifier: Programming Language :: Python :: 3.13
Classifier: Programming Language :: Python :: 3.14
Classifier: Topic :: Scientific/Engineering :: Atmospheric Science
Classifier: Topic :: Scientific/Engineering :: Visualization
Classifier: Typing :: Typed
Requires-Python: >=3.12
Requires-Dist: matplotlib>=3.8.0
Requires-Dist: numpy>=1.26.0
Provides-Extra: dev
Requires-Dist: pyright>=1.1.405; extra == 'dev'
Requires-Dist: pytest-cov>=4.0.0; extra == 'dev'
Requires-Dist: pytest>=8.0.0; extra == 'dev'
Requires-Dist: ruff>=0.13.1; extra == 'dev'
